cbsplotlib/__init__.py
cbsplotlib/colors.py
cbsplotlib/highcharts.py
cbsplotlib/htmlviewer.py
cbsplotlib/settings.py
cbsplotlib/utils.py
cbsplotlib/cbs_hc_defaults/area_percentage_grouped.json
cbsplotlib/cbs_hc_defaults/area_stacked_grouped.json
cbsplotlib/cbs_hc_defaults/bar.json
cbsplotlib/cbs_hc_defaults/bar_percentage.json
cbsplotlib/cbs_hc_defaults/bar_stacked.json
cbsplotlib/cbs_hc_defaults/bar_stacked_percentage.json
cbsplotlib/cbs_hc_defaults/bar_with_negative_stack.json
cbsplotlib/cbs_hc_defaults/bubblechart_tourist.json
cbsplotlib/cbs_hc_defaults/choropleth_youthcare.json
cbsplotlib/cbs_hc_defaults/column.json
cbsplotlib/cbs_hc_defaults/column_grouped.json
cbsplotlib/cbs_hc_defaults/column_grouped_stacked.json
cbsplotlib/cbs_hc_defaults/column_grouped_stacked_percentage.json
cbsplotlib/cbs_hc_defaults/column_percentage.json
cbsplotlib/cbs_hc_defaults/column_stacked.json
cbsplotlib/cbs_hc_defaults/column_stacked_percentage.json
cbsplotlib/cbs_hc_defaults/highcharts_view.html
cbsplotlib/cbs_hc_defaults/line.json
cbsplotlib/cbs_hc_defaults/line_column_combination_grouped.json
cbsplotlib/cbs_hc_defaults/pie_donut.json
cbsplotlib/cbs_hc_defaults/polar_spider_line.json
cbsplotlib/cbs_hc_defaults/spline_grouped.json
cbsplotlib-0.5.9.dist-info/METADATA
cbsplotlib-0.5.9.dist-info/WHEEL
cbsplotlib-0.5.9.dist-info/entry_points.txt
cbsplotlib-0.5.9.dist-info/licenses/AUTHORS.rst
cbsplotlib-0.5.9.dist-info/licenses/LICENSE.txt
cbsplotlib-0.5.9.dist-info/RECORD
