Metadata-Version: 2.3
Name: cbsplotlib
Version: 0.5.9
Summary: Frontend to matplotlib to create pictures in the CBS corporate identity
Project-URL: Documentation, https://pyscaffold.org/
Project-URL: Homepage, https://github.com/pyscaffold/pyscaffold/
Author-email: Eelco van Vliet <eelcovv@gmail.nl>
License: MIT
Classifier: Development Status :: 4 - Beta
Classifier: Programming Language :: Python
Requires-Python: >=3.8
Requires-Dist: matplotlib
Requires-Dist: numpy
Requires-Dist: pandas
Requires-Dist: seaborn
Provides-Extra: dev
Requires-Dist: black; extra == 'dev'
Requires-Dist: pre-commit; extra == 'dev'
Requires-Dist: pytest; extra == 'dev'
Requires-Dist: pytest-cov; extra == 'dev'
Requires-Dist: ruff>=0.8.0; extra == 'dev'
Requires-Dist: twine; extra == 'dev'
Requires-Dist: wheel; extra == 'dev'
Provides-Extra: testing
Requires-Dist: pytest; extra == 'testing'
Requires-Dist: pytest-cov; extra == 'testing'
